composer_hr/__init__.py
composer_hr/engine/__init__.py
composer_hr/engine/abstract.py
composer_hr/engine/base.py
composer_hr/engine/element.py
composer_hr/engine/enum.py
composer_hr/engine/functions.py
composer_hr/engine/renderer.py
composer_hr/middleware.py
composer_hr/routes.py
composer_hr/utils.py
composer_hr-0.1.0.dist-info/LICENSE
composer_hr-0.1.0.dist-info/WHEEL
composer_hr-0.1.0.dist-info/METADATA
composer_hr-0.1.0.dist-info/RECORD
