Metadata-Version: 2.1
Name: composer-hr
Version: 0.1.0
Summary: Composer for Eletronic Health Records
License: MIT
Author: Daniel Arantes
Requires-Python: >=3.8,<4.0
Classifier: License :: OSI Approved :: MIT License
Classifier: Programming Language :: Python :: 3
Classifier: Programming Language :: Python :: 3.8
Classifier: Programming Language :: Python :: 3.9
Requires-Dist: Markdown (>=3.3.4,<4.0.0)
Requires-Dist: requests-html (>=0.10.0,<0.11.0)
Requires-Dist: responder (>=2.0.7,<3.0.0)
Requires-Dist: typesystem (>=0.2.4,<0.3.0)
